segram/__init__.py
segram/abc.py
segram/about.py
segram/settings.py
segram/symbols.py
segram/datastruct/__init__.py
segram/datastruct/collections.py
segram/datastruct/namespace.py
segram/grammar/__init__.py
segram/grammar/abc.py
segram/grammar/components.py
segram/grammar/conjuncts.py
segram/grammar/doc.py
segram/grammar/graph.py
segram/grammar/phrases.py
segram/grammar/sent.py
segram/grammar/lang/__init__.py
segram/grammar/lang/en/__init__.py
segram/grammar/lang/en/components.py
segram/grammar/lang/en/doc.py
segram/grammar/lang/en/grammar.py
segram/grammar/lang/en/phrases.py
segram/grammar/lang/en/sent.py
segram/nlp/__init__.py
segram/nlp/corpus.py
segram/nlp/backend/__init__.py
segram/nlp/backend/rulebased/__init__.py
segram/nlp/backend/rulebased/lang/__init__.py
segram/nlp/backend/rulebased/lang/en/__init__.py
segram/nlp/backend/rulebased/lang/en/grammar/__init__.py
segram/nlp/backend/rulebased/lang/en/grammar/components.py
segram/nlp/backend/rulebased/lang/en/grammar/doc.py
segram/nlp/backend/rulebased/lang/en/grammar/grammar.py
segram/nlp/backend/rulebased/lang/en/grammar/phrases.py
segram/nlp/backend/rulebased/lang/en/grammar/sent.py
segram/nlp/backend/rulebased/lang/en/pipeline/__init__.py
segram/nlp/backend/rulebased/lang/en/pipeline/factories.py
segram/nlp/backend/rulebased/lang/en/pipeline/lemmatizer/__init__.py
segram/nlp/backend/rulebased/lang/en/pipeline/lemmatizer/patterns.json.gz
segram/nlp/backend/rulebased/lang/en/pipeline/merger/__init__.py
segram/nlp/backend/rulebased/lang/en/pipeline/merger/patterns.json.gz
segram/nlp/backend/rulebased/lang/en/tokens/__init__.py
segram/nlp/backend/rulebased/lang/en/tokens/token.py
segram/nlp/extensions/__init__.py
segram/nlp/extensions/base.py
segram/nlp/grammar/__init__.py
segram/nlp/grammar/components.py
segram/nlp/grammar/doc.py
segram/nlp/grammar/grammar.py
segram/nlp/grammar/phrases.py
segram/nlp/grammar/sent.py
segram/nlp/pipeline/__init__.py
segram/nlp/pipeline/annotator.py
segram/nlp/pipeline/base.py
segram-0.0.0.dist-info/LICENSE
segram-0.0.0.dist-info/METADATA
segram-0.0.0.dist-info/WHEEL
segram-0.0.0.dist-info/entry_points.txt
segram-0.0.0.dist-info/top_level.txt
segram-0.0.0.dist-info/RECORD
