Metadata-Version: 2.1
Name: segram
Version: 0.0.0
Summary: A framework for semantic grammar and narrative analysis.
Author-email: Szymon Talaga <stalaga@protonmail.com>
License: Copyright (c) 2023 Szymon Talaga
Project-URL: documentation, https://segram.readthedocs.io/en/latest/
Project-URL: repository, https://github.com/sztal/segram
Project-URL: changelog, https://github.com/sztal/segram/blob/master/CHANGELOG.md
Keywords: natural language processing,NLP,narratives,narrative analysis,semantics,syntax,grammar
Classifier: Development Status :: 3 - Alpha
Classifier: Environment :: Console
Classifier: Environment :: GPU
Classifier: Environment :: GPU :: NVIDIA CUDA
Classifier: Intended Audience :: Developers
Classifier: Intended Audience :: Science/Research
Classifier: License :: OSI Approved :: MIT License
Classifier: Natural Language :: English
Classifier: Operating System :: OS Independent
Classifier: Programming Language :: Python :: 3.11
Classifier: Topic :: Scientific/Engineering :: Artificial Intelligence
Classifier: Topic :: Scientific/Engineering :: Information Analysis
Classifier: Topic :: Scientific/Engineering :: Visualization
Requires-Python: >=3.11
License-File: LICENSE
Requires-Dist: spacy >=3.4
Requires-Dist: more-itertools >=8.0
Provides-Extra: coref
Requires-Dist: spacy <3.5,>=3.4 ; extra == 'coref'
Requires-Dist: spacy-experimental ==0.6.3 ; extra == 'coref'
Provides-Extra: gpu
Requires-Dist: cupy ; extra == 'gpu'
